{"frames": {

"star0001.png":
{
	"frame": {"x":0,"y":0,"w":256,"h":256},
	"rotated": false,
	"trimmed": false,
	"spriteSourceSize": {"x":0,"y":0,"w":256,"h":256},
	"sourceSize": {"w":256,"h":256},
	"pivot": {"x":0.5,"y":0.5}
},
"star0002.png":
{
	"frame": {"x":256,"y":0,"w":256,"h":256},
	"rotated": false,
	"trimmed": false,
	"spriteSourceSize": {"x":0,"y":0,"w":256,"h":256},
	"sourceSize": {"w":256,"h":256},
	"pivot": {"x":0.5,"y":0.5}
},
"star0003.png":
{
	"frame": {"x":512,"y":0,"w":256,"h":256},
	"rotated": false,
	"trimmed": false,
	"spriteSourceSize": {"x":0,"y":0,"w":256,"h":256},
	"sourceSize": {"w":256,"h":256},
	"pivot": {"x":0.5,"y":0.5}
},
"star0004.png":
{
	"frame": {"x":768,"y":0,"w":256,"h":256},
	"rotated": false,
	"trimmed": false,
	"spriteSourceSize": {"x":0,"y":0,"w":256,"h":256},
	"sourceSize": {"w":256,"h":256},
	"pivot": {"x":0.5,"y":0.5}
},
"star0005.png":
{
	"frame": {"x":1024,"y":0,"w":256,"h":256},
	"rotated": false,
	"trimmed": false,
	"spriteSourceSize": {"x":0,"y":0,"w":256,"h":256},
	"sourceSize": {"w":256,"h":256},
	"pivot": {"x":0.5,"y":0.5}
},
"star0006.png":
{
	"frame": {"x":1280,"y":0,"w":256,"h":256},
	"rotated": false,
	"trimmed": false,
	"spriteSourceSize": {"x":0,"y":0,"w":256,"h":256},
	"sourceSize": {"w":256,"h":256},
	"pivot": {"x":0.5,"y":0.5}
},
"star0007.png":
{
	"frame": {"x":1536,"y":0,"w":256,"h":256},
	"rotated": false,
	"trimmed": false,
	"spriteSourceSize": {"x":0,"y":0,"w":256,"h":256},
	"sourceSize": {"w":256,"h":256},
	"pivot": {"x":0.5,"y":0.5}
},
"star0008.png":
{
	"frame": {"x":1792,"y":0,"w":256,"h":256},
	"rotated": false,
	"trimmed": false,
	"spriteSourceSize": {"x":0,"y":0,"w":256,"h":256},
	"sourceSize": {"w":256,"h":256},
	"pivot": {"x":0.5,"y":0.5}
},
"star0009.png":
{
	"frame": {"x":0,"y":256,"w":256,"h":256},
	"rotated": false,
	"trimmed": false,
	"spriteSourceSize": {"x":0,"y":0,"w":256,"h":256},
	"sourceSize": {"w":256,"h":256},
	"pivot": {"x":0.5,"y":0.5}
},
"star0010.png":
{
	"frame": {"x":256,"y":256,"w":256,"h":256},
	"rotated": false,
	"trimmed": false,
	"spriteSourceSize": {"x":0,"y":0,"w":256,"h":256},
	"sourceSize": {"w":256,"h":256},
	"pivot": {"x":0.5,"y":0.5}
},
"star0011.png":
{
	"frame": {"x":512,"y":256,"w":256,"h":256},
	"rotated": false,
	"trimmed": false,
	"spriteSourceSize": {"x":0,"y":0,"w":256,"h":256},
	"sourceSize": {"w":256,"h":256},
	"pivot": {"x":0.5,"y":0.5}
},
"star0012.png":
{
	"frame": {"x":768,"y":256,"w":256,"h":256},
	"rotated": false,
	"trimmed": false,
	"spriteSourceSize": {"x":0,"y":0,"w":256,"h":256},
	"sourceSize": {"w":256,"h":256},
	"pivot": {"x":0.5,"y":0.5}
},
"star0013.png":
{
	"frame": {"x":1024,"y":256,"w":256,"h":256},
	"rotated": false,
	"trimmed": false,
	"spriteSourceSize": {"x":0,"y":0,"w":256,"h":256},
	"sourceSize": {"w":256,"h":256},
	"pivot": {"x":0.5,"y":0.5}
},
"star0014.png":
{
	"frame": {"x":1280,"y":256,"w":256,"h":256},
	"rotated": false,
	"trimmed": false,
	"spriteSourceSize": {"x":0,"y":0,"w":256,"h":256},
	"sourceSize": {"w":256,"h":256},
	"pivot": {"x":0.5,"y":0.5}
},
"star0015.png":
{
	"frame": {"x":1536,"y":256,"w":256,"h":256},
	"rotated": false,
	"trimmed": false,
	"spriteSourceSize": {"x":0,"y":0,"w":256,"h":256},
	"sourceSize": {"w":256,"h":256},
	"pivot": {"x":0.5,"y":0.5}
},
"star0016.png":
{
	"frame": {"x":1792,"y":256,"w":256,"h":256},
	"rotated": false,
	"trimmed": false,
	"spriteSourceSize": {"x":0,"y":0,"w":256,"h":256},
	"sourceSize": {"w":256,"h":256},
	"pivot": {"x":0.5,"y":0.5}
},
"star0017.png":
{
	"frame": {"x":0,"y":512,"w":256,"h":256},
	"rotated": false,
	"trimmed": false,
	"spriteSourceSize": {"x":0,"y":0,"w":256,"h":256},
	"sourceSize": {"w":256,"h":256},
	"pivot": {"x":0.5,"y":0.5}
},
"star0018.png":
{
	"frame": {"x":256,"y":512,"w":256,"h":256},
	"rotated": false,
	"trimmed": false,
	"spriteSourceSize": {"x":0,"y":0,"w":256,"h":256},
	"sourceSize": {"w":256,"h":256},
	"pivot": {"x":0.5,"y":0.5}
},
"star0019.png":
{
	"frame": {"x":512,"y":512,"w":256,"h":256},
	"rotated": false,
	"trimmed": false,
	"spriteSourceSize": {"x":0,"y":0,"w":256,"h":256},
	"sourceSize": {"w":256,"h":256},
	"pivot": {"x":0.5,"y":0.5}
},
"star0020.png":
{
	"frame": {"x":768,"y":512,"w":256,"h":256},
	"rotated": false,
	"trimmed": false,
	"spriteSourceSize": {"x":0,"y":0,"w":256,"h":256},
	"sourceSize": {"w":256,"h":256},
	"pivot": {"x":0.5,"y":0.5}
},
"star0021.png":
{
	"frame": {"x":1024,"y":512,"w":256,"h":256},
	"rotated": false,
	"trimmed": false,
	"spriteSourceSize": {"x":0,"y":0,"w":256,"h":256},
	"sourceSize": {"w":256,"h":256},
	"pivot": {"x":0.5,"y":0.5}
},
"star0022.png":
{
	"frame": {"x":1280,"y":512,"w":256,"h":256},
	"rotated": false,
	"trimmed": false,
	"spriteSourceSize": {"x":0,"y":0,"w":256,"h":256},
	"sourceSize": {"w":256,"h":256},
	"pivot": {"x":0.5,"y":0.5}
},
"star0023.png":
{
	"frame": {"x":1536,"y":512,"w":256,"h":256},
	"rotated": false,
	"trimmed": false,
	"spriteSourceSize": {"x":0,"y":0,"w":256,"h":256},
	"sourceSize": {"w":256,"h":256},
	"pivot": {"x":0.5,"y":0.5}
},
"star0024.png":
{
	"frame": {"x":1792,"y":512,"w":256,"h":256},
	"rotated": false,
	"trimmed": false,
	"spriteSourceSize": {"x":0,"y":0,"w":256,"h":256},
	"sourceSize": {"w":256,"h":256},
	"pivot": {"x":0.5,"y":0.5}
}},
"meta": {
	"app": "https://www.codeandweb.com/texturepacker",
	"version": "1.0",
	"image": "star.png",
	"format": "RGBA8888",
	"size": {"w":2048,"h":768},
	"scale": "1",
	"smartupdate": "$TexturePacker:SmartUpdate:28319ebaf292a06919c55b5b88870a8e:f352f9ce8783caf63a3598a90bc4c9e9:24daf5f0426eb704a6b44d07225f8860$"
}
}
